[
  {
    "full_name": "GoogleChromeLabs/proxx",
    "stargazers_count": 1049,
    "open_issues_count": 103,
    "forks_count": 93
  },
  {
    "full_name": "GoogleChromeLabs/dark-mode-toggle",
    "stargazers_count": 486,
    "open_issues_count": 0,
    "forks_count": 29
  },
  {
    "full_name": "GoogleChromeLabs/tooling.report",
    "stargazers_count": 517,
    "open_issues_count": 76,
    "forks_count": 21
  },
  {
    "full_name": "storybookjs/storybook",
    "stargazers_count": 54797,
    "open_issues_count": 822,
    "forks_count": 5512
  }
]